<?xml version="1.0"?>
<building name="MacIntire Hall">
	<card type="spring_fling">
        <image url="http://wheatoncollege.edu/college-history/files/2011/02/mcintire_back_1-122x122.jpg"></image>
        <text>McIntire Hall</text>
    </card>
    <card type ="secret_agent">
        <image url="http://wheatoncollege.edu/college-history/files/2011/02/mcintire_5-122x122.jpg"></image> 
        <text>The second residence hall to be built on lower campus.</text>
        <text>Named after Walter Oscar McIntire.</text>
    </card>

</building>
